easypour/__init__.py
easypour/cli.py
easypour/core.py
easypour/ieee.py
easypour/inline.py
easypour/mathstub.py
easypour/pdfmixins.py
easypour/render.py
easypour-0.1.0.dist-info/METADATA
easypour-0.1.0.dist-info/WHEEL
easypour-0.1.0.dist-info/entry_points.txt
easypour-0.1.0.dist-info/licenses/LICENSE
easypour-0.1.0.dist-info/RECORD
