Metadata-Version: 2.4
Name: EasyPour
Version: 0.1.0
Summary: Write markdown report easily! Optionally transform into a PDF, streamlit page, or dash page!
Project-URL: Homepage, https://github.com/ESPR3SS0/EasyPour
Project-URL: Repository, https://github.com/ESPR3SS0/EasyPour
Author-email: ESPR3SS0 <98864173+ESPR3SS0@users.noreply.github.com>
License: MIT License
License-File: LICENSE
Requires-Python: >=3.9
Requires-Dist: build<2,>=1.3.0
Requires-Dist: markdown-it-py<5,>=4.0.0
Requires-Dist: reportlab<5,>=4.4.4
Provides-Extra: cli
Requires-Dist: cyclopts<3,>=2.7; extra == 'cli'
Provides-Extra: dash
Requires-Dist: dash<4,>=3.2.0; extra == 'dash'
Provides-Extra: dev
Requires-Dist: pytest<9,>=8.4.2; extra == 'dev'
Requires-Dist: ruff<0.7,>=0.6.0; extra == 'dev'
Provides-Extra: docs
Requires-Dist: mkdocs-material<10,>=9.6.22; extra == 'docs'
Requires-Dist: mkdocs<2,>=1.6.1; extra == 'docs'
Requires-Dist: pymdown-extensions<11,>=10.12; extra == 'docs'
Provides-Extra: plots
Requires-Dist: matplotlib; extra == 'plots'
Provides-Extra: streamlit
Requires-Dist: streamlit<2,>=1.50.0; extra == 'streamlit'
Provides-Extra: weasy
Requires-Dist: weasyprint<67,>=66.0; extra == 'weasy'
